maestro/__init__.py
maestro/aws/__init__.py
maestro/aws/cf_stack.py
maestro/aws/dynamodb.py
maestro/aws/parameter_store.py
maestro/aws/r53.py
maestro/aws/s3.py
maestro/aws/ssm_documents.py
maestro/core/__init__.py
maestro/core/execute.py
maestro/core/ioc.py
maestro/core/module.py
maestro/jenkins/__init__.py
maestro/jenkins/jobs.py
maestro/tools/__init__.py
maestro/tools/file.py
maestro/tools/os_tools.py
maestro/tools/path.py
maestro/tools/string.py
MaestroOps-0.9.3.dist-info/LICENSE
MaestroOps-0.9.3.dist-info/METADATA
MaestroOps-0.9.3.dist-info/WHEEL
MaestroOps-0.9.3.dist-info/top_level.txt
MaestroOps-0.9.3.dist-info/RECORD
